{
    "closures": [
        {
            "year": "2022",
            "week1": "Monday, 29 August 2022 - Monday, 26 September 2022",
            "week2": "Saturday, 1 October 2022",
            "week3": "Thursday, 24 November 2022",
            "week4": "Saturday, 24 December 2022",
            "week5": "Saturday, 31 December 2022"
        },

        {
            "year": "2023",
            "week1": "Monday, 13 March 2023 - Monday, 20 March 2023",
            "week2": "Saturday, 1 April 2023",
            "week3": "Tuesday, 4 July 2023",
            "week4": "Monday, 14 August 2023 - Monday, 18 December 2023"
        }
    ]
}